{
    "country_name": "Norway",
    "country_id": "NO",
    "provinces": [
        {
            "province_name": "Finnmark Fylke",
            "cities": [
                {
                    "city_name": "Tana"
                },
                {
                    "city_name": "Sor-Varanger"
                },
                {
                    "city_name": "Nordkapp"
                },
                {
                    "city_name": "Nesseby"
                },
                {
                    "city_name": "Masoy"
                },
                {
                    "city_name": "Loppa"
                },
                {
                    "city_name": "Lebesby"
                },
                {
                    "city_name": "Kvalsund"
                },
                {
                    "city_name": "Kautokeino"
                },
                {
                    "city_name": "Karasjok"
                },
                {
                    "city_name": "Hasvik"
                },
                {
                    "city_name": "Gamvik"
                },
                {
                    "city_name": "Berlevag"
                },
                {
                    "city_name": "Batsfjord"
                },
                {
                    "city_name": "Alta"
                },
                {
                    "city_name": "Hammerfest"
                },
                {
                    "city_name": "Vardo"
                },
                {
                    "city_name": "Porsanger"
                },
                {
                    "city_name": "Vadso"
                }
            ]
        },
        {
            "province_name": "Vestfold fylke",
            "cities": [
                {
                    "city_name": "Re"
                },
                {
                    "city_name": "Tjome"
                },
                {
                    "city_name": "Notteroy"
                },
                {
                    "city_name": "Horten"
                },
                {
                    "city_name": "Svelvik"
                },
                {
                    "city_name": "Sande"
                },
                {
                    "city_name": "Hof"
                },
                {
                    "city_name": "Holmestrand"
                },
                {
                    "city_name": "Lardal"
                },
                {
                    "city_name": "Tonsberg"
                },
                {
                    "city_name": "Larvik"
                },
                {
                    "city_name": "Sandefjord"
                }
            ]
        },
        {
            "province_name": "Vest-Agder Fylke",
            "cities": [
                {
                    "city_name": "Vennesla"
                },
                {
                    "city_name": "Audnedal"
                },
                {
                    "city_name": "Sogne"
                },
                {
                    "city_name": "Sirdal"
                },
                {
                    "city_name": "Lyngdal"
                },
                {
                    "city_name": "Kvinesdal"
                },
                {
                    "city_name": "Haegebostad"
                },
                {
                    "city_name": "Aseral"
                },
                {
                    "city_name": "Flekkefjord"
                },
                {
                    "city_name": "Marnardal"
                },
                {
                    "city_name": "Songdalen"
                },
                {
                    "city_name": "Farsund"
                },
                {
                    "city_name": "Lindesnes"
                },
                {
                    "city_name": "Kristiansand"
                },
                {
                    "city_name": "Mandal"
                }
            ]
        },
        {
            "province_name": "Troms Fylke",
            "cities": [
                {
                    "city_name": "Storfjord"
                },
                {
                    "city_name": "Skjervoy"
                },
                {
                    "city_name": "Nordreisa"
                },
                {
                    "city_name": "Lyngen"
                },
                {
                    "city_name": "Kvaenangen"
                },
                {
                    "city_name": "Karlsoy"
                },
                {
                    "city_name": "Kafjord"
                },
                {
                    "city_name": "Tranoy"
                },
                {
                    "city_name": "Torsken"
                },
                {
                    "city_name": "Sorreisa"
                },
                {
                    "city_name": "Skanland"
                },
                {
                    "city_name": "Salangen"
                },
                {
                    "city_name": "Malselv"
                },
                {
                    "city_name": "Lenvik"
                },
                {
                    "city_name": "Lavangen"
                },
                {
                    "city_name": "Kvaefjord"
                },
                {
                    "city_name": "Ibestad"
                },
                {
                    "city_name": "Gratangen"
                },
                {
                    "city_name": "Dyroy"
                },
                {
                    "city_name": "Bardu"
                },
                {
                    "city_name": "Balsfjord"
                },
                {
                    "city_name": "Tromso"
                },
                {
                    "city_name": "Berg"
                },
                {
                    "city_name": "Harstad"
                }
            ]
        },
        {
            "province_name": "Telemark fylke",
            "cities": [
                {
                    "city_name": "Tinn"
                },
                {
                    "city_name": "Siljan"
                },
                {
                    "city_name": "Seljord"
                },
                {
                    "city_name": "Sauherad"
                },
                {
                    "city_name": "Nissedal"
                },
                {
                    "city_name": "Kviteseid"
                },
                {
                    "city_name": "Kragero"
                },
                {
                    "city_name": "Hjartdal"
                },
                {
                    "city_name": "Fyresdal"
                },
                {
                    "city_name": "Drangedal"
                },
                {
                    "city_name": "Bamble"
                },
                {
                    "city_name": "Vinje"
                },
                {
                    "city_name": "Notodden"
                },
                {
                    "city_name": "Tokke"
                },
                {
                    "city_name": "Bo"
                },
                {
                    "city_name": "Skien"
                },
                {
                    "city_name": "Nome"
                },
                {
                    "city_name": "Porsgrunn"
                }
            ]
        },
        {
            "province_name": "Sor-Trondelag Fylke",
            "cities": [
                {
                    "city_name": "Tydal"
                },
                {
                    "city_name": "Trondheim"
                },
                {
                    "city_name": "Snillfjord"
                },
                {
                    "city_name": "Skaun"
                },
                {
                    "city_name": "Selbu"
                },
                {
                    "city_name": "Roan"
                },
                {
                    "city_name": "Rissa"
                },
                {
                    "city_name": "Rennebu"
                },
                {
                    "city_name": "Osen"
                },
                {
                    "city_name": "Orland"
                },
                {
                    "city_name": "Orkdal"
                },
                {
                    "city_name": "Oppdal"
                },
                {
                    "city_name": "Melhus"
                },
                {
                    "city_name": "Meldal"
                },
                {
                    "city_name": "Malvik"
                },
                {
                    "city_name": "Klaebu"
                },
                {
                    "city_name": "Hitra"
                },
                {
                    "city_name": "Hemne"
                },
                {
                    "city_name": "Holtalen"
                },
                {
                    "city_name": "Bjugn"
                },
                {
                    "city_name": "Agdenes"
                },
                {
                    "city_name": "Afjord"
                },
                {
                    "city_name": "Froya"
                },
                {
                    "city_name": "Midtre Gauldal"
                },
                {
                    "city_name": "Roros"
                }
            ]
        },
        {
            "province_name": "Sogn og Fjordane Fylke",
            "cities": [
                {
                    "city_name": "Vik"
                },
                {
                    "city_name": "Stryn"
                },
                {
                    "city_name": "Solund"
                },
                {
                    "city_name": "Sogndal"
                },
                {
                    "city_name": "Selje"
                },
                {
                    "city_name": "Naustdal"
                },
                {
                    "city_name": "Luster"
                },
                {
                    "city_name": "Leikanger"
                },
                {
                    "city_name": "Laerdal"
                },
                {
                    "city_name": "Jolster"
                },
                {
                    "city_name": "Hyllestad"
                },
                {
                    "city_name": "Hoyanger"
                },
                {
                    "city_name": "Hornindal"
                },
                {
                    "city_name": "Gulen"
                },
                {
                    "city_name": "Gloppen"
                },
                {
                    "city_name": "Gaular"
                },
                {
                    "city_name": "Forde"
                },
                {
                    "city_name": "Flora"
                },
                {
                    "city_name": "Fjaler"
                },
                {
                    "city_name": "Bremanger"
                },
                {
                    "city_name": "Balestrand"
                },
                {
                    "city_name": "Aurland"
                },
                {
                    "city_name": "Askvoll"
                },
                {
                    "city_name": "Vagsoy"
                },
                {
                    "city_name": "Eid"
                },
                {
                    "city_name": "Ardal"
                }
            ]
        },
        {
            "province_name": "Rogaland Fylke",
            "cities": [
                {
                    "city_name": "Utsira"
                },
                {
                    "city_name": "Tysvaer"
                },
                {
                    "city_name": "Time"
                },
                {
                    "city_name": "Strand"
                },
                {
                    "city_name": "Sola"
                },
                {
                    "city_name": "Sokndal"
                },
                {
                    "city_name": "Sauda"
                },
                {
                    "city_name": "Rennesoy"
                },
                {
                    "city_name": "Randaberg"
                },
                {
                    "city_name": "Lund"
                },
                {
                    "city_name": "Kvitsoy"
                },
                {
                    "city_name": "Klepp"
                },
                {
                    "city_name": "Hjelmeland"
                },
                {
                    "city_name": "Ha"
                },
                {
                    "city_name": "Gjesdal"
                },
                {
                    "city_name": "Forsand"
                },
                {
                    "city_name": "Finnoy"
                },
                {
                    "city_name": "Eigersund"
                },
                {
                    "city_name": "Bokn"
                },
                {
                    "city_name": "Bjerkreim"
                },
                {
                    "city_name": "Suldal"
                },
                {
                    "city_name": "Vindafjord"
                },
                {
                    "city_name": "Haugesund"
                },
                {
                    "city_name": "Karmoy"
                },
                {
                    "city_name": "Stavanger"
                },
                {
                    "city_name": "Sandnes"
                }
            ]
        },
        {
            "province_name": "Ostfold fylke",
            "cities": [
                {
                    "city_name": "Trogstad"
                },
                {
                    "city_name": "Spydeberg"
                },
                {
                    "city_name": "Skiptvet"
                },
                {
                    "city_name": "Rygge"
                },
                {
                    "city_name": "Romskog"
                },
                {
                    "city_name": "Rakkestad"
                },
                {
                    "city_name": "Rade"
                },
                {
                    "city_name": "Hvaler"
                },
                {
                    "city_name": "Hobol"
                },
                {
                    "city_name": "Eidsberg"
                },
                {
                    "city_name": "Askim"
                },
                {
                    "city_name": "Aremark"
                },
                {
                    "city_name": "Marker"
                },
                {
                    "city_name": "Moss"
                },
                {
                    "city_name": "Valer"
                },
                {
                    "city_name": "Sarpsborg"
                },
                {
                    "city_name": "Fredrikstad"
                },
                {
                    "city_name": "Halden"
                }
            ]
        },
        {
            "province_name": "Oslo County",
            "cities": [
                {
                    "city_name": "Oslo"
                }
            ]
        },
        {
            "province_name": "Oppland fylke",
            "cities": [
                {
                    "city_name": "Vestre Toten"
                },
                {
                    "city_name": "Vestre Slidre"
                },
                {
                    "city_name": "Vaga"
                },
                {
                    "city_name": "Sor-Fron"
                },
                {
                    "city_name": "Sor-Aurdal"
                },
                {
                    "city_name": "Sondre Land"
                },
                {
                    "city_name": "Skjak"
                },
                {
                    "city_name": "Sel"
                },
                {
                    "city_name": "Ringebu"
                },
                {
                    "city_name": "Oystre Slidre"
                },
                {
                    "city_name": "Oyer"
                },
                {
                    "city_name": "Ostre Toten"
                },
                {
                    "city_name": "Nordre Land"
                },
                {
                    "city_name": "Nord-Fron"
                },
                {
                    "city_name": "Nord-Aurdal"
                },
                {
                    "city_name": "Lunner"
                },
                {
                    "city_name": "Lom"
                },
                {
                    "city_name": "Lesja"
                },
                {
                    "city_name": "Jevnaker"
                },
                {
                    "city_name": "Gran"
                },
                {
                    "city_name": "Gausdal"
                },
                {
                    "city_name": "Etnedal"
                },
                {
                    "city_name": "Dovre"
                },
                {
                    "city_name": "Vang"
                },
                {
                    "city_name": "Lillehammer"
                },
                {
                    "city_name": "Gjovik"
                }
            ]
        },
        {
            "province_name": "Nord-Trondelag Fylke",
            "cities": [
                {
                    "city_name": "Vikna"
                },
                {
                    "city_name": "Verran"
                },
                {
                    "city_name": "Verdal"
                },
                {
                    "city_name": "Stjordal"
                },
                {
                    "city_name": "Steinkjer"
                },
                {
                    "city_name": "Snasa"
                },
                {
                    "city_name": "Royrvik"
                },
                {
                    "city_name": "Overhalla"
                },
                {
                    "city_name": "Namsskogan"
                },
                {
                    "city_name": "Namdalseid"
                },
                {
                    "city_name": "Naeroy"
                },
                {
                    "city_name": "Meraker"
                },
                {
                    "city_name": "Leksvik"
                },
                {
                    "city_name": "Leka"
                },
                {
                    "city_name": "Inderoy"
                },
                {
                    "city_name": "Hoylandet"
                },
                {
                    "city_name": "Grong"
                },
                {
                    "city_name": "Frosta"
                },
                {
                    "city_name": "Fosnes"
                },
                {
                    "city_name": "Flatanger"
                },
                {
                    "city_name": "Lierne"
                },
                {
                    "city_name": "Namsos"
                },
                {
                    "city_name": "Levanger"
                }
            ]
        },
        {
            "province_name": "Nordland Fylke",
            "cities": [
                {
                    "city_name": "Vevelstad"
                },
                {
                    "city_name": "Vefsn"
                },
                {
                    "city_name": "Vagan"
                },
                {
                    "city_name": "Vaeroy"
                },
                {
                    "city_name": "Tysfjord"
                },
                {
                    "city_name": "Traena"
                },
                {
                    "city_name": "Tjeldsund"
                },
                {
                    "city_name": "Steigen"
                },
                {
                    "city_name": "Sortland"
                },
                {
                    "city_name": "Sorfold"
                },
                {
                    "city_name": "Somna"
                },
                {
                    "city_name": "Saltdal"
                },
                {
                    "city_name": "Rost"
                },
                {
                    "city_name": "Rodoy"
                },
                {
                    "city_name": "Oksnes"
                },
                {
                    "city_name": "Nesna"
                },
                {
                    "city_name": "Moskenes"
                },
                {
                    "city_name": "Meloy"
                },
                {
                    "city_name": "Luroy"
                },
                {
                    "city_name": "Lodingen"
                },
                {
                    "city_name": "Leirfjord"
                },
                {
                    "city_name": "Hemnes"
                },
                {
                    "city_name": "Hattfjelldal"
                },
                {
                    "city_name": "Hamaroy"
                },
                {
                    "city_name": "Hadsel"
                },
                {
                    "city_name": "Grane"
                },
                {
                    "city_name": "Gildeskal"
                },
                {
                    "city_name": "Flakstad"
                },
                {
                    "city_name": "Fauske"
                },
                {
                    "city_name": "Evenes"
                },
                {
                    "city_name": "Donna"
                },
                {
                    "city_name": "Bronnoy"
                },
                {
                    "city_name": "Bindal"
                },
                {
                    "city_name": "Beiarn"
                },
                {
                    "city_name": "Ballangen"
                },
                {
                    "city_name": "Alstahaug"
                },
                {
                    "city_name": "Andoy"
                },
                {
                    "city_name": "Bo"
                },
                {
                    "city_name": "Narvik"
                },
                {
                    "city_name": "Vestvagoy"
                },
                {
                    "city_name": "Bodo"
                },
                {
                    "city_name": "Rana"
                },
                {
                    "city_name": "Heroy"
                },
                {
                    "city_name": "Vega"
                }
            ]
        },
        {
            "province_name": "More og Romsdal fylke",
            "cities": [
                {
                    "city_name": "Volda"
                },
                {
                    "city_name": "Vanylven"
                },
                {
                    "city_name": "Ulstein"
                },
                {
                    "city_name": "Tingvoll"
                },
                {
                    "city_name": "Sykkylven"
                },
                {
                    "city_name": "Surnadal"
                },
                {
                    "city_name": "Sunndal"
                },
                {
                    "city_name": "Stranda"
                },
                {
                    "city_name": "Stordal"
                },
                {
                    "city_name": "Smola"
                },
                {
                    "city_name": "Skodje"
                },
                {
                    "city_name": "Sandoy"
                },
                {
                    "city_name": "Rindal"
                },
                {
                    "city_name": "Orsta"
                },
                {
                    "city_name": "Orskog"
                },
                {
                    "city_name": "Norddal"
                },
                {
                    "city_name": "Nesset"
                },
                {
                    "city_name": "Molde"
                },
                {
                    "city_name": "Hareid"
                },
                {
                    "city_name": "Haram"
                },
                {
                    "city_name": "Halsa"
                },
                {
                    "city_name": "Gjemnes"
                },
                {
                    "city_name": "Giske"
                },
                {
                    "city_name": "Fraena"
                },
                {
                    "city_name": "Aure"
                },
                {
                    "city_name": "Kristiansund"
                },
                {
                    "city_name": "Averoy"
                },
                {
                    "city_name": "Eide"
                },
                {
                    "city_name": "Aukra"
                },
                {
                    "city_name": "Midsund"
                },
                {
                    "city_name": "Rauma"
                },
                {
                    "city_name": "Vestnes"
                },
                {
                    "city_name": "Heroy"
                },
                {
                    "city_name": "Alesund"
                },
                {
                    "city_name": "Sula"
                },
                {
                    "city_name": "Sande"
                }
            ]
        },
        {
            "province_name": "Hordaland Fylke",
            "cities": [
                {
                    "city_name": "Voss"
                },
                {
                    "city_name": "Ulvik"
                },
                {
                    "city_name": "Ullensvang"
                },
                {
                    "city_name": "Tysnes"
                },
                {
                    "city_name": "Sveio"
                },
                {
                    "city_name": "Sund"
                },
                {
                    "city_name": "Stord"
                },
                {
                    "city_name": "Samnanger"
                },
                {
                    "city_name": "Odda"
                },
                {
                    "city_name": "Modalen"
                },
                {
                    "city_name": "Meland"
                },
                {
                    "city_name": "Masfjorden"
                },
                {
                    "city_name": "Lindas"
                },
                {
                    "city_name": "Kvinnherad"
                },
                {
                    "city_name": "Kvam"
                },
                {
                    "city_name": "Jondal"
                },
                {
                    "city_name": "Granvin"
                },
                {
                    "city_name": "Fusa"
                },
                {
                    "city_name": "Fjell"
                },
                {
                    "city_name": "Fitjar"
                },
                {
                    "city_name": "Fedje"
                },
                {
                    "city_name": "Etne"
                },
                {
                    "city_name": "Eidfjord"
                },
                {
                    "city_name": "Bomlo"
                },
                {
                    "city_name": "Bergen"
                },
                {
                    "city_name": "Austrheim"
                },
                {
                    "city_name": "Austevoll"
                },
                {
                    "city_name": "Askoy"
                },
                {
                    "city_name": "Vaksdal"
                },
                {
                    "city_name": "Oygarden"
                },
                {
                    "city_name": "Radoy"
                },
                {
                    "city_name": "Osteroy"
                },
                {
                    "city_name": "Os"
                }
            ]
        },
        {
            "province_name": "Hedmark fylke",
            "cities": [
                {
                    "city_name": "Tynset"
                },
                {
                    "city_name": "Trysil"
                },
                {
                    "city_name": "Stor-Elvdal"
                },
                {
                    "city_name": "Stange"
                },
                {
                    "city_name": "Sor-Odal"
                },
                {
                    "city_name": "Ringsaker"
                },
                {
                    "city_name": "Rendalen"
                },
                {
                    "city_name": "Nord-Odal"
                },
                {
                    "city_name": "Loten"
                },
                {
                    "city_name": "Kongsvinger"
                },
                {
                    "city_name": "Grue"
                },
                {
                    "city_name": "Folldal"
                },
                {
                    "city_name": "Engerdal"
                },
                {
                    "city_name": "Elverum"
                },
                {
                    "city_name": "Eidskog"
                },
                {
                    "city_name": "Asnes"
                },
                {
                    "city_name": "Amot"
                },
                {
                    "city_name": "Alvdal"
                },
                {
                    "city_name": "Os"
                },
                {
                    "city_name": "Tolga"
                },
                {
                    "city_name": "Hamar"
                },
                {
                    "city_name": "Valer"
                }
            ]
        },
        {
            "province_name": "Buskerud fylke",
            "cities": [
                {
                    "city_name": "Sigdal"
                },
                {
                    "city_name": "Royken"
                },
                {
                    "city_name": "Rollag"
                },
                {
                    "city_name": "Ovre Eiker"
                },
                {
                    "city_name": "Nedre Eiker"
                },
                {
                    "city_name": "Modum"
                },
                {
                    "city_name": "Lier"
                },
                {
                    "city_name": "Krodsherad"
                },
                {
                    "city_name": "Hurum"
                },
                {
                    "city_name": "Hemsedal"
                },
                {
                    "city_name": "Gol"
                },
                {
                    "city_name": "Flesberg"
                },
                {
                    "city_name": "Al"
                },
                {
                    "city_name": "Hol"
                },
                {
                    "city_name": "Nes"
                },
                {
                    "city_name": "Ringerike"
                },
                {
                    "city_name": "Fla"
                },
                {
                    "city_name": "Nore og Uvdal"
                },
                {
                    "city_name": "Hole"
                },
                {
                    "city_name": "Drammen"
                },
                {
                    "city_name": "Kongsberg"
                }
            ]
        },
        {
            "province_name": "Aust-Agder fylke",
            "cities": [
                {
                    "city_name": "Lillesand"
                },
                {
                    "city_name": "Vegarshei"
                },
                {
                    "city_name": "Valle"
                },
                {
                    "city_name": "Tvedestrand"
                },
                {
                    "city_name": "Iveland"
                },
                {
                    "city_name": "Gjerstad"
                },
                {
                    "city_name": "Froland"
                },
                {
                    "city_name": "Evje og Hornnes"
                },
                {
                    "city_name": "Bykle"
                },
                {
                    "city_name": "Bygland"
                },
                {
                    "city_name": "Birkenes"
                },
                {
                    "city_name": "Amli"
                },
                {
                    "city_name": "Risor"
                },
                {
                    "city_name": "Arendal"
                },
                {
                    "city_name": "Grimstad"
                }
            ]
        },
        {
            "province_name": "Akershus fylke",
            "cities": [
                {
                    "city_name": "Vestby"
                },
                {
                    "city_name": "Ullensaker"
                },
                {
                    "city_name": "Sorum"
                },
                {
                    "city_name": "Ski"
                },
                {
                    "city_name": "Skedsmo"
                },
                {
                    "city_name": "Raelingen"
                },
                {
                    "city_name": "Oppegard"
                },
                {
                    "city_name": "Nittedal"
                },
                {
                    "city_name": "Nesodden"
                },
                {
                    "city_name": "Nannestad"
                },
                {
                    "city_name": "Lorenskog"
                },
                {
                    "city_name": "Hurdal"
                },
                {
                    "city_name": "Gjerdrum"
                },
                {
                    "city_name": "Frogn"
                },
                {
                    "city_name": "Fet"
                },
                {
                    "city_name": "Enebakk"
                },
                {
                    "city_name": "Eidsvoll"
                },
                {
                    "city_name": "Baerum"
                },
                {
                    "city_name": "Asker"
                },
                {
                    "city_name": "As"
                },
                {
                    "city_name": "Nes"
                },
                {
                    "city_name": "Aurskog-Holand"
                }
            ]
        }
    ]
}